Full_Adder/Verilog/Descriptive.v

`timescale 1ns/1ns


module full_adder (output s , output c , input inA , input inB , input cin);
wire x ,y ,z ;
xor(x,inA,inB);
and(y,inA,inB);
xor(s,x,cin);
and(z,x,cin);
or(c,z,y);
endmodule

Full_Adder/Verilog/testbench.v
`timescale 1ns/1ns
module full_add_tb();
  reg a,b,d;
  wire s , c;
  full_adder full_add(s,c,a,b,d);
   initial begin
     $dumpfile("dump.vcd");
     $dumpvars(2,full_add_tb);
    a=0;
    b=0;
    d=0;
    #100 
     $display("a=%d .b=%d , h_add=%d , h_carry=%d" , a,b,s,c);
    a=0;
    b=0;
    d=1;
    #100 
     $display("a=%d .b=%d , h_add=%d , h_carry=%d" , a,b,s,c);
    a=0;
    b=1;
    d=0;
    #100 
     $display("a=%d .b=%d , h_add=%d , h_carry=%d" , a,b,s,c);
    a=0;
    b=1;
    d=1;
    #100 
     $display("a=%d .b=%d , h_add=%d , h_carry=%d" , a,b,s,c);
    a=1;
    b=0;
    d=0;
    #100 
     $display("a=%d .b=%d , h_add=%d , h_carry=%d" , a,b,s,c);
    a=1;
    b=0;
    d=1;
    #100 
     $display("a=%d .b=%d , h_add=%d , h_carry=%d" , a,b,s,c);
    a=1;
    b=1;
    d=0;
    #100 
     $display("a=%d .b=%d , h_add=%d , h_carry=%d" , a,b,s,c);
    a=1;
    b=1;
    d=1;
    #100 
     $display("a=%d .b=%d , h_add=%d , h_carry=%d" , a,b,s,c);
    $finish;
  end
endmodule

Full_Adder/Verilog/dump.vcd
$date
	Wed Oct 12 05:05:39 2022
$end
$version
	ModelSim Version 2020.1
$end
$timescale
	1ns
$end

$scope module full_add_tb $end
$var reg 1 ! a $end
$var reg 1 " b $end
$var reg 1 # d $end
$var wire 1 $ s $end
$var wire 1 % c $end

$scope module full_add $end
$var wire 1 $ s $end
$var wire 1 % c $end
$var wire 1 & inA $end
$var wire 1 ' inB $end
$var wire 1 ( cin $end
$var wire 1 ) x $end
$var wire 1 * y $end
$var wire 1 + z $end
$upscope $end
$upscope $end
$enddefinitions $end
#0
$dumpvars
0!
0"
0#
0$
0%
0)
0*
0+
0(
0'
0&
$end
#100
1#
1(
1$
#200
1"
0#
1'
0(
1)
0$
1$
#300
1#
1(
1+
0$
1%
#400
1!
0"
0#
1&
0'
0(
0+
1$
0%
#500
1#
1(
1+
0$
1%
#600
1"
0#
1'
0(
1*
0)
0+
1$
0$
#700
1#
1(
1$
